README
setup.py
mwuppet/__init__.py
mwuppet/mwuppet.py
python_mwuppet.egg-info/PKG-INFO
python_mwuppet.egg-info/SOURCES.txt
python_mwuppet.egg-info/dependency_links.txt
python_mwuppet.egg-info/entry_points.txt
python_mwuppet.egg-info/requires.txt
python_mwuppet.egg-info/top_level.txt