Metadata-Version: 1.0
Name: python-mwuppet
Version: 0.0.4
Summary:  Mediawiki UserScript Deploy Script
Home-page: https://github.com/yuvipanda/mwuppet
Author: Yuvi Panda
Author-email: yuvipanda@gmail.com
License: MIT License
Platform: UNKNOWN
